cnspy_trajectory/BsplineSE3.py
cnspy_trajectory/HistoryBuffer.py
cnspy_trajectory/PlotLineStyle.py
cnspy_trajectory/PlotTrajectory.py
cnspy_trajectory/ROSBag_Pose.py
cnspy_trajectory/SpatialConverter.py
cnspy_trajectory/Trajectory.py
cnspy_trajectory/TrajectoryBase.py
cnspy_trajectory/TrajectoryError.py
cnspy_trajectory/TrajectoryErrorType.py
cnspy_trajectory/TrajectoryEstimated.py
cnspy_trajectory/TrajectoryEstimationError.py
cnspy_trajectory/TrajectoryPlotConfig.py
cnspy_trajectory/TrajectoryPlotTypes.py
cnspy_trajectory/TrajectoryPlotUtils.py
cnspy_trajectory/TrajectoryPlotter.py
cnspy_trajectory/__init__.py
cnspy_trajectory/pyplot_utils.py
test/__init__.py
test/test_BsplineSE3.py
test/test_HistoryBuffer.py
test/test_SpatialConverter.py
test/test_Trajectory.py
test/test_TrajectoryError.py
test/test_TrajectoryErrorType.py
test/test_TrajectoryEstimated.py
test/test_TrajectoryPlotter.py
cnspy_trajectory-0.2.14.dist-info/LICENCE
cnspy_trajectory-0.2.14.dist-info/METADATA
cnspy_trajectory-0.2.14.dist-info/WHEEL
cnspy_trajectory-0.2.14.dist-info/entry_points.txt
cnspy_trajectory-0.2.14.dist-info/top_level.txt
cnspy_trajectory-0.2.14.dist-info/RECORD
