Metadata-Version: 2.1
Name: cnspy_trajectory
Version: 0.2.14
Summary: Trajectory in SE(3) space with utilities.
Home-page: https://github.com/aau-cns/cnspy_trajectory/
Author: Roland Jung
Author-email: roland.jung@aau.at
Project-URL: Bug Tracker, https://github.com/aau-cns/cnspy_trajectory/issues
Classifier: Development Status :: 4 - Beta
Classifier: Intended Audience :: Developers
Classifier: Programming Language :: Python :: 3
Classifier: License :: OSI Approved :: GNU General Public License v3 (GPLv3)
Classifier: Operating System :: OS Independent
Requires-Python: >=3.6
License-File: LICENCE
Requires-Dist: numpy
Requires-Dist: matplotlib
Requires-Dist: cnspy-csv2dataframe >=0.2.2
Requires-Dist: spatialmath-python
Requires-Dist: cnspy-spatial-csv-formats >=0.2.2
